file_organizer/__init__.py
file_organizer/main.py
file_organizer_advanced-1.0.2.dist-info/METADATA
file_organizer_advanced-1.0.2.dist-info/WHEEL
file_organizer_advanced-1.0.2.dist-info/entry_points.txt
file_organizer_advanced-1.0.2.dist-info/top_level.txt
file_organizer_advanced-1.0.2.dist-info/RECORD
