Metadata-Version: 2.4
Name: file-organizer-advanced
Version: 1.0.2
Summary: A CLI tool to automatically organize files into categorized folders
Home-page: https://github.com/vikram-mistry/file-organizer
Author: Vikram Mistry
Author-email: Vick <youremail@example.com>
License-Expression: MIT
Keywords: file,organizer,cli,automation,python,folder,sort
Classifier: Programming Language :: Python :: 3
Classifier: Operating System :: OS Independent
Requires-Python: >=3.6
Dynamic: author
Dynamic: home-page
Dynamic: requires-python
